{
  "_schema": "src/lib/data.ts#HistoryData",
  "entries": [
    {
      "date": "1979-01-31",
      "score": 7
    },
    {
      "date": "1980-01-31",
      "score": 0
    },
    {
      "date": "1981-01-31",
      "score": 3
    },
    {
      "date": "1982-01-31",
      "score": 1
    },
    {
      "date": "1983-01-31",
      "score": 0
    },
    {
      "date": "1984-01-31",
      "score": 0
    },
    {
      "date": "1985-01-31",
      "score": 0
    },
    {
      "date": "1986-01-31",
      "score": 3
    },
    {
      "date": "1987-01-31",
      "score": 4
    },
    {
      "date": "1988-01-31",
      "score": 0
    },
    {
      "date": "1989-01-31",
      "score": 1
    },
    {
      "date": "1990-01-31",
      "score": 5
    },
    {
      "date": "1991-01-31",
      "score": 38
    },
    {
      "date": "1992-01-31",
      "score": 1
    },
    {
      "date": "1993-01-31",
      "score": 19
    },
    {
      "date": "1994-01-31",
      "score": 7
    },
    {
      "date": "1995-01-31",
      "score": 27
    },
    {
      "date": "1996-01-31",
      "score": 16
    },
    {
      "date": "1997-01-31",
      "score": 30
    },
    {
      "date": "1998-01-31",
      "score": 13
    },
    {
      "date": "1999-01-31",
      "score": 30
    },
    {
      "date": "2000-01-31",
      "score": 21
    },
    {
      "date": "2000-04-30",
      "score": 11
    },
    {
      "date": "2000-07-31",
      "score": 30
    },
    {
      "date": "2000-10-31",
      "score": 28
    },
    {
      "date": "2001-01-31",
      "score": 13
    },
    {
      "date": "2001-04-30",
      "score": 28
    },
    {
      "date": "2001-07-31",
      "score": 25
    },
    {
      "date": "2001-10-31",
      "score": 34
    },
    {
      "date": "2002-01-31",
      "score": 25
    },
    {
      "date": "2002-04-30",
      "score": 28
    },
    {
      "date": "2002-07-31",
      "score": 39
    },
    {
      "date": "2002-10-31",
      "score": 29
    },
    {
      "date": "2003-01-31",
      "score": 41
    },
    {
      "date": "2003-04-30",
      "score": 45
    },
    {
      "date": "2003-07-31",
      "score": 30
    },
    {
      "date": "2003-10-31",
      "score": 20
    },
    {
      "date": "2004-01-31",
      "score": 25
    },
    {
      "date": "2004-04-30",
      "score": 20
    },
    {
      "date": "2004-07-31",
      "score": 32
    },
    {
      "date": "2004-10-31",
      "score": 26
    },
    {
      "date": "2005-01-31",
      "score": 22
    },
    {
      "date": "2005-04-30",
      "score": 26
    },
    {
      "date": "2005-07-31",
      "score": 26
    },
    {
      "date": "2005-10-31",
      "score": 19
    },
    {
      "date": "2006-01-31",
      "score": 25
    },
    {
      "date": "2006-04-30",
      "score": 17
    },
    {
      "date": "2006-07-31",
      "score": 45
    },
    {
      "date": "2006-10-31",
      "score": 40
    },
    {
      "date": "2007-01-31",
      "score": 50
    },
    {
      "date": "2007-04-30",
      "score": 41
    },
    {
      "date": "2007-07-31",
      "score": 65
    },
    {
      "date": "2007-10-31",
      "score": 49
    },
    {
      "date": "2008-01-31",
      "score": 81
    },
    {
      "date": "2008-04-30",
      "score": 76
    },
    {
      "date": "2008-07-31",
      "score": 57
    },
    {
      "date": "2008-10-31",
      "score": 63
    },
    {
      "date": "2009-01-31",
      "score": 49
    },
    {
      "date": "2009-04-30",
      "score": 42
    },
    {
      "date": "2009-07-31",
      "score": 51
    },
    {
      "date": "2009-10-31",
      "score": 48
    },
    {
      "date": "2010-01-31",
      "score": 39
    },
    {
      "date": "2010-04-30",
      "score": 48
    },
    {
      "date": "2010-07-31",
      "score": 36
    },
    {
      "date": "2010-10-31",
      "score": 42
    },
    {
      "date": "2011-01-31",
      "score": 47
    },
    {
      "date": "2011-04-30",
      "score": 52
    },
    {
      "date": "2011-07-31",
      "score": 53
    },
    {
      "date": "2011-10-31",
      "score": 49
    },
    {
      "date": "2012-01-31",
      "score": 68
    },
    {
      "date": "2012-04-30",
      "score": 49
    },
    {
      "date": "2012-07-31",
      "score": 35
    },
    {
      "date": "2012-10-31",
      "score": 42
    },
    {
      "date": "2013-01-31",
      "score": 59
    },
    {
      "date": "2013-04-30",
      "score": 54
    },
    {
      "date": "2013-07-31",
      "score": 41
    },
    {
      "date": "2013-10-31",
      "score": 62
    },
    {
      "date": "2014-01-31",
      "score": 61
    },
    {
      "date": "2014-04-30",
      "score": 65
    },
    {
      "date": "2014-07-31",
      "score": 56
    },
    {
      "date": "2014-10-31",
      "score": 60
    },
    {
      "date": "2015-01-31",
      "score": 40
    },
    {
      "date": "2015-04-30",
      "score": 59
    },
    {
      "date": "2015-07-31",
      "score": 66
    },
    {
      "date": "2015-10-31",
      "score": 64
    },
    {
      "date": "2016-01-31",
      "score": 66
    },
    {
      "date": "2016-04-30",
      "score": 57
    },
    {
      "date": "2016-07-31",
      "score": 57
    },
    {
      "date": "2016-10-31",
      "score": 59
    },
    {
      "date": "2017-01-31",
      "score": 54
    },
    {
      "date": "2017-04-30",
      "score": 58
    },
    {
      "date": "2017-07-31",
      "score": 52
    },
    {
      "date": "2017-10-31",
      "score": 61
    },
    {
      "date": "2018-01-31",
      "score": 54
    },
    {
      "date": "2018-04-30",
      "score": 61
    },
    {
      "date": "2018-07-31",
      "score": 57
    },
    {
      "date": "2018-10-31",
      "score": 57
    },
    {
      "date": "2019-01-31",
      "score": 56
    },
    {
      "date": "2019-04-30",
      "score": 53
    },
    {
      "date": "2019-07-31",
      "score": 74
    },
    {
      "date": "2019-10-31",
      "score": 80
    },
    {
      "date": "2020-01-31",
      "score": 94
    },
    {
      "date": "2020-04-30",
      "score": 77
    },
    {
      "date": "2020-07-31",
      "score": 68
    },
    {
      "date": "2020-10-31",
      "score": 56
    },
    {
      "date": "2021-01-31",
      "score": 62
    },
    {
      "date": "2021-04-30",
      "score": 57
    },
    {
      "date": "2021-07-31",
      "score": 59
    },
    {
      "date": "2021-10-31",
      "score": 49
    },
    {
      "date": "2022-01-31",
      "score": 56
    },
    {
      "date": "2022-04-30",
      "score": 55
    },
    {
      "date": "2022-07-31",
      "score": 69
    },
    {
      "date": "2022-10-31",
      "score": 57
    },
    {
      "date": "2023-01-31",
      "score": 61
    },
    {
      "date": "2023-04-30",
      "score": 47
    },
    {
      "date": "2023-07-31",
      "score": 51
    },
    {
      "date": "2023-10-31",
      "score": 61
    },
    {
      "date": "2024-01-31",
      "score": 74
    },
    {
      "date": "2024-04-30",
      "score": 59
    },
    {
      "date": "2024-07-31",
      "score": 63
    },
    {
      "date": "2024-10-31",
      "score": 58
    },
    {
      "date": "2025-01-31",
      "score": 68
    },
    {
      "date": "2025-04-30",
      "score": 72
    },
    {
      "date": "2025-07-31",
      "score": 64
    },
    {
      "date": "2025-10-31",
      "score": 59
    },
    {
      "date": "2025-12-31",
      "score": 69
    }
  ]
}